<?xml version="1.0" encoding="UTF-8"?>
<beans xmlns="http://www.springframework.org/schema/beans"
	xmlns:xsi="http://www.w3.org/2001/XMLSchema-instance"
	xmlns:context="http://www.springframework.org/schema/context"
	xsi:schemaLocation="http://www.springframework.org/schema/beans http://www.springframework.org/schema/beans/spring-beans.xsd
		http://www.springframework.org/schema/context http://www.springframework.org/schema/context/spring-context-3.1.xsd">

	<bean id="compassGps" class="org.compass.gps.impl.SingleCompassGps" init-method="start" destroy-method="stop">
		<property name="compass" ref="compass"/>
		<property name="gpsDevices">
			<list>
				<ref local="jpaGpsDevice"/>
			</list>
		</property>
	</bean>
	
	<bean id="jpaGpsDevice" class="org.compass.gps.device.jpa.JpaGpsDevice">
		<property name="name" value="jpaDevice"/>
		<property name="entityManagerFactory" ref="emf"/>
		<property name="nativeExtractor">
			<bean class="org.compass.gps.device.jpa.extractor.SpringNativeJpaExtractor"/>
		</property>
	</bean>
	
	<bean id="compass" class="org.compass.spring.LocalCompassBean">
		<property name="mappingScan" value="org.roguepanda.mod.domain"/>
		<property name="transactionManager" ref="transactionManager"/>
		<property name="dataSource" ref="dataSource"/>
		<property name="compassSettings">
			<props>
				<prop key="compass.engine.connection">${user.home}/.mod-repo-index</prop>
				<prop key="compass.transaction.factory">org.compass.spring.transaction.SpringSyncTransactionFactory</prop>
				<prop key="compass.engine.spellcheck.enable">true</prop>
				<prop key="compass.osem.supportUnmarshall">false</prop>
			</props>
		</property>
	</bean>
	
	<context:property-placeholder/>
	
</beans>
